{
  "anim_adjust_params": {
    "anim_mode": "all",
    "direction": ""
  },
  "category_id": "ruchang",
  "category_name": "In",
  "duration": 500000,
  "id": "7054480742507614722",
  "material_type": "sticker",
  "name": "Zoom Out 2",
  "panel": "",
  "path": "C:/Users/tqk2811/AppData/Local/CapCut/User Data/Cache/effect/7054480742507614722/d57145a34871f239c1512d7c748e3131",
  "platform": "all",
  "request_id": "202512191543392C62ED75E842E059CE3C",
  "resource_id": "7054480742507614722",
  "source_platform": 1,
  "start": 0,
  "third_resource_id": "7054480742507614722",
  "type": "in"
}