{
  "category_id": "2037709433",
  "category_name": "Classic",
  "duration": 3266666,
  "effect_id": "7521649607093374269",
  "id": "131B2138-1A34-4c58-B9D2-3A50E5360869",
  "is_ai_transition": false,
  "is_overlap": true,
  "name": "Overlap Fade",
  "path": "%userprofile%/AppData/Local/CapCut/User Data/Cache/effect/7521649607093374269/9b2388f9320df9ad5187983b72d5aa71",
  "platform": "all",
  "request_id": "20251218111449233459D8396809E0DCBC",
  "resource_id": "7521649607093374269",
  "source_platform": 1,
  "task_id": "",
  "third_resource_id": "0",
  "type": "transition",
  "video_path": ""
}