{
  "category_id": "25835",
  "category_name": "Trending",
  "duration": 1466666,
  "effect_id": "7535363967414193425",
  "id": "B2EFB3B7-1F12-4b93-A1E7-3B01A87D17A5",
  "is_ai_transition": false,
  "is_overlap": true,
  "name": "Shuriken Switch",
  "path": "%userprofile%/AppData/Local/CapCut/User Data/Cache/effect/7535363967414193425/ad77c35b735cf652306f7da43e14fcfa",
  "platform": "all",
  "request_id": "20251229081335AB86CE996891FD075E06",
  "resource_id": "7535363967414193425",
  "source_platform": 1,
  "task_id": "",
  "third_resource_id": "0",
  "type": "transition",
  "video_path": ""
}